jupyter_ros_server/__init__.py
jupyter_ros_server/_version.py
jupyter_ros_server/jupyter_ros_server.json
jupyter_ros_server/api/__init__.py
jupyter_ros_server/api/bridge.py
jupyter_ros_server/api/launch.py
jupyter_ros_server/api/master.py
jupyter_ros_server/api/pkgs.py
jupyter_ros_server/api/setting.py
jupyter_ros_server/lib/__init__.py
jupyter_ros_server/lib/bag.py
jupyter_ros_server/lib/process.py
jupyter_ros_server/lib/settings.py
jupyter_ros_server/public/1.index.ca02d1e5aa763bbf70de.js
jupyter_ros_server/public/1.index.ca02d1e5aa763bbf70de.js.map
jupyter_ros_server/public/2b9b4872cd25494093c1eb14f0264a0b.svg
jupyter_ros_server/public/5bbcdfca599323ba0603.module.wasm
jupyter_ros_server/public/EditorControls.js
jupyter_ros_server/public/favicon.ico
jupyter_ros_server/public/index.ca02d1e5aa763bbf70de.js
jupyter_ros_server/public/index.ca02d1e5aa763bbf70de.js.map
jupyter_ros_server/public/index.html
jupyter_ros_server/public/logo.svg
jupyter_ros_server/public/screenshot.png
jupyter_ros_server/public/zethus.svg
jupyter_ros_server/public/zethus_full.svg
jupyter_ros_server/public/zethus_mark.svg
jupyter_ros_server/public/forklift/forklift.stl
jupyter_ros_server/public/image/viz/viz-image.png
jupyter_ros_server/public/image/viz/viz-interactive-marker.png
jupyter_ros_server/public/image/viz/viz-laserscan.png
jupyter_ros_server/public/image/viz/viz-map.png
jupyter_ros_server/public/image/viz/viz-marker.png
jupyter_ros_server/public/image/viz/viz-markerarray.png
jupyter_ros_server/public/image/viz/viz-odometry.png
jupyter_ros_server/public/image/viz/viz-path.png
jupyter_ros_server/public/image/viz/viz-point.png
jupyter_ros_server/public/image/viz/viz-pointcloud.png
jupyter_ros_server/public/image/viz/viz-pose.png
jupyter_ros_server/public/image/viz/viz-posearray.png
jupyter_ros_server/public/image/viz/viz-range.png
jupyter_ros_server/public/image/viz/viz-robotmodel.png
jupyter_ros_server/public/image/viz/viz-tf.png
jupyter_ros_server/public/image/viz/viz-wrench.png
jupyter_ros_server-0.1.1.dist-info/LICENSE
jupyter_ros_server-0.1.1.dist-info/METADATA
jupyter_ros_server-0.1.1.dist-info/WHEEL
jupyter_ros_server-0.1.1.dist-info/top_level.txt
jupyter_ros_server-0.1.1.dist-info/RECORD
